pokermgr/__init__.py
pokermgr/action.py
pokermgr/analysis.py
pokermgr/board.py
pokermgr/evaluate.py
pokermgr/funcs.py
pokermgr/game.py
pokermgr/game_base.py
pokermgr/game_plo.py
pokermgr/game_plo_bomb.py
pokermgr/game_plo_regular.py
pokermgr/game_result.py
pokermgr/game_simulator.py
pokermgr/game_simulator_plo_bomb.py
pokermgr/game_simulator_plo_regular.py
pokermgr/game_simulator_texas_holdem_bomb.py
pokermgr/game_simulator_texas_holdem_regular.py
pokermgr/game_street.py
pokermgr/game_texas_holdem.py
pokermgr/game_texas_holdem_bomb.py
pokermgr/game_texas_holdem_regular.py
pokermgr/hand.py
pokermgr/hole_cards.py
pokermgr/omaha_hand_evaluator.py
pokermgr/player.py
pokermgr/pot.py
pokermgr/py.typed
pokermgr/table.py
pokermgr-3.4.0.dist-info/LICENSE
pokermgr-3.4.0.dist-info/METADATA
pokermgr-3.4.0.dist-info/WHEEL
pokermgr-3.4.0.dist-info/RECORD
