Metadata-Version: 2.3
Name: pokermgr
Version: 3.4.0
Summary: Comprehensive Python library for managing poker games
Keywords: poker,texas-holdem,omaha,card-games,game-evaluation
Author: Bhadresh Dahanuwala
Author-email: bhadresh.dahanuwala@gmail.com
Requires-Python: >=3.10
Classifier: Development Status :: 4 - Beta
Classifier: Intended Audience :: Developers
Classifier: License :: OSI Approved :: MIT License
Classifier: Programming Language :: Python :: 3
Classifier: Programming Language :: Python :: 3.10
Classifier: Programming Language :: Python :: 3.11
Classifier: Programming Language :: Python :: 3.12
Classifier: Topic :: Games/Entertainment
Classifier: Topic :: Software Development :: Libraries :: Python Modules
Classifier: Typing :: Typed
Provides-Extra: dev
Requires-Dist: cardspy (>=2.0.0,<3.0.0)
Requires-Dist: flake8 (>=7.2.0) ; extra == "dev"
Requires-Dist: mypy (>=1.16.0) ; extra == "dev"
Requires-Dist: pylint (>=3.3.7) ; extra == "dev"
Requires-Dist: pytest (>=8.3.5) ; extra == "dev"
